{
	"name": "as186113_dataflow1",
	"properties": {
		"type": "MappingDataFlow",
		"typeProperties": {
			"sources": [
				{
					"dataset": {
						"referenceName": "as186113_demo_file1",
						"type": "DatasetReference"
					},
					"name": "source1"
				}
			],
			"sinks": [],
			"transformations": [
				{
					"name": "DerivedColumn1"
				}
			],
			"script": "source(output(\n\t\t{Flight#^Origin^Dest^FlightDate^NoSalesReason^TransmittingFlightAttd} as string\n\t),\n\tallowSchemaDrift: true,\n\tvalidateSchema: false,\n\twildcardPaths:['input/*.*']) ~> source1\nsource1 derive(Firstname = upper(byNames(FirstName, Achal))) ~> DerivedColumn1"
		}
	}
}