{
	"name": "MS186104_Demo1",
	"properties": {
		"activities": [
			{
				"name": "CopyData",
				"type": "Copy",
				"dependsOn": [],
				"policy": {
					"timeout": "7.00:00:00",
					"retry": 0,
					"retryIntervalInSeconds": 30,
					"secureOutput": false,
					"secureInput": false
				},
				"userProperties": [],
				"typeProperties": {
					"source": {
						"type": "JsonSource",
						"storeSettings": {
							"type": "AzureBlobFSReadSettings",
							"recursive": true,
							"wildcardFolderPath": "Inbound",
							"wildcardFileName": "Aircraft_Flown*.json"
						},
						"formatSettings": {
							"type": "JsonReadSettings"
						}
					},
					"enableStaging": false
				},
				"inputs": [
					{
						"referenceName": "Aircraft_Flown_Src",
						"type": "DatasetReference"
					}
				]
			}
		],
		"folder": {
			"name": "MS186104"
		},
		"annotations": []
	}
}