{
	"name": "ctl_file_ds",
	"properties": {
		"linkedServiceName": {
			"referenceName": "blob_ls",
			"type": "LinkedServiceReference"
		},
		"parameters": {
			"ctl_file_name": {
				"type": "string"
			},
			"ctl_folder_path": {
				"type": "string"
			}
		},
		"annotations": [],
		"type": "DelimitedText",
		"typeProperties": {
			"location": {
				"type": "AzureBlobStorageLocation",
				"fileName": {
					"value": "@dataset().ctl_file_name",
					"type": "Expression"
				},
				"container": {
					"value": "@dataset().ctl_folder_path",
					"type": "Expression"
				}
			},
			"columnDelimiter": ",",
			"escapeChar": "\\",
			"quoteChar": "\""
		},
		"schema": [
			{
				"type": "String"
			}
		]
	}
}